attmap/__init__.py
attmap/_att_map_like.py
attmap/_version.py
attmap/attmap.py
attmap/attmap_echo.py
attmap/helpers.py
attmap/ordattmap.py
attmap/pathex_attmap.py
attmap-0.13.2.dist-info/LICENSE.txt
attmap-0.13.2.dist-info/METADATA
attmap-0.13.2.dist-info/WHEEL
attmap-0.13.2.dist-info/top_level.txt
attmap-0.13.2.dist-info/RECORD
