Metadata-Version: 2.1
Name: attmap
Version: 0.13.2
Summary: Multiple access patterns for key-value reference
Home-page: https://github.com/pepkit/attmap/
Author: Nathan Sheffield, Vince Reuter, Michal Stolarczyk
License: BSD2
Keywords: dict,map,mapping,dot,item,getitem,attr,getattr,key-value,dynamic,mutable,access
Platform: UNKNOWN
Classifier: Development Status :: 4 - Beta
Classifier: License :: OSI Approved :: BSD License
Classifier: Programming Language :: Python :: 2.7
Classifier: Programming Language :: Python :: 3.5
Classifier: Programming Language :: Python :: 3.6
License-File: LICENSE.txt
